CHANGELOG.rst
COPYING
COPYING.LESSER
MANIFEST.in
README.rst
setup.py
fmn/__init__.py
fmn.rules.egg-info/PKG-INFO
fmn.rules.egg-info/SOURCES.txt
fmn.rules.egg-info/dependency_links.txt
fmn.rules.egg-info/namespace_packages.txt
fmn.rules.egg-info/not-zip-safe
fmn.rules.egg-info/pbr.json
fmn.rules.egg-info/requires.txt
fmn.rules.egg-info/top_level.txt
fmn/rules/__init__.py
fmn/rules/anitya.py
fmn/rules/ansible.py
fmn/rules/askbot.py
fmn/rules/autocloud.py
fmn/rules/bodhi.py
fmn/rules/bugzilla.py
fmn/rules/buildsys.py
fmn/rules/compose.py
fmn/rules/coprs.py
fmn/rules/faf.py
fmn/rules/fas.py
fmn/rules/fedbadges.py
fmn/rules/fedimg.py
fmn/rules/fedocal.py
fmn/rules/fedora_elections.py
fmn/rules/fedoratagger.py
fmn/rules/fmn_notifications.py
fmn/rules/generic.py
fmn/rules/git.py
fmn/rules/github.py
fmn/rules/hotness.py
fmn/rules/infragit.py
fmn/rules/jenkins.py
fmn/rules/kerneltest.py
fmn/rules/koschei.py
fmn/rules/logger.py
fmn/rules/mailman.py
fmn/rules/mdapi.py
fmn/rules/meetbot.py
fmn/rules/nagios.py
fmn/rules/nuancier.py
fmn/rules/pagure.py
fmn/rules/pkgdb.py
fmn/rules/planet.py
fmn/rules/summershum.py
fmn/rules/taskotron.py
fmn/rules/trac.py
fmn/rules/utils.py
fmn/rules/wiki.py