Metadata-Version: 1.1
Name: fmn.rules
Version: 0.9.1
Summary: Message processing rules for Fedora Notifications
Home-page: https://github.com/fedora-infra/fmn.rules
Author: Ralph Bean
Author-email: rbean@redhat.com
License: LGPLv2+
Download-URL: https://pypi.python.org/pypi/fmn.rules/
Platform: UNKNOWN
Classifier: Environment :: Web Environment
Classifier: Topic :: Software Development :: Libraries :: Python Modules
Classifier: Intended Audience :: Developers
Classifier: Programming Language :: Python
